{
    "how-to-implement": "in your meta.json - define *extended* with url to this (json) file - https://raw.githubusercontent.com/cardanians/adapools.org/master/example-meta.json",
    "info": {
        "url_png_icon_64x64": "https://www.linkpicture.com/q/MAYZJPEG.jpg",
        "url_png_logo": "https://www.linkpicture.com/q/MAYZJPEG.jpg",
        "location": "Patagonia, Argentina",
        "social": {
            "twitter_handle": "@MAYZprotocol",
            "telegram_handle": "",
            "facebook_handle": "",
            "youtube_handle": "",
            "twitch_handle": "",
            "discord_handle": "https://discord.gg/zTCmeMXC",
            "github_handle": ""
        },
        "company": {
            "name": "MAYZ Protocol ISPO Staking Pool",
            "addr": "",
            "city": "Patagonia",
            "country": "Argentina",
            "company_id": "",
            "vat_id": ""
        },
        "about": {
            "me": "This is the MAYZ Protocol ISPO. Delegate ADA and get $MAYZ rewards with increased APY vs the regular ADA estimated APY",
            "server": "We are operating using Virtual Machines with a total of 2 Relay Nodes and 1 Bare Metal Block Producer Node, located in Patagonia, Argentina.",
            "company": "."
        }
    }
}
